meshutility/__init__.py
meshutility/colormap.py
meshutility/isocurve.py
meshutility/mesh2graph.py
meshutility/mesh_cut.py
meshutility/mesh_split.py
meshutility/obj_lines_io.py
meshutility/pygeodesic.cpython-36m-darwin.so
meshutility/pyisocurve.cpython-36m-darwin.so
meshutility/pyremesh.cpython-36m-darwin.so
meshutility/pyshapeop.cpython-36m-darwin.so
meshutility/remove_unreferenced.py
meshutility/sphere_cvt.py
meshutility/split_connected_components.py
meshutility/utils.cpython-36m-darwin.so
meshutility-0.0.2.dist-info/LICENSE
meshutility-0.0.2.dist-info/LICENSE.BSD2
meshutility-0.0.2.dist-info/LICENSE.MPL2
meshutility-0.0.2.dist-info/LICENSE.OpenMesh
meshutility-0.0.2.dist-info/LICENSE.pybind11
meshutility-0.0.2.dist-info/METADATA
meshutility-0.0.2.dist-info/WHEEL
meshutility-0.0.2.dist-info/top_level.txt
meshutility-0.0.2.dist-info/RECORD
