Metadata-Version: 2.1
Name: meshutility
Version: 0.0.2
Summary: A collection of python utilities for mesh processing
Home-page: https://github.com/zishun/MeshUtility
Author: Zishun Liu
Author-email: 
License: UNKNOWN
Project-URL: Bug Tracker, https://github.com/zishun/MeshUtility/issues
Platform: UNKNOWN
Classifier: Programming Language :: Python :: 3
Classifier: License :: OSI Approved :: GNU Lesser General Public License v2 or later (LGPLv2+)
Classifier: Operating System :: OS Independent
Classifier: Topic :: Multimedia :: Graphics :: 3D Modeling
Requires-Python: >=3.6
License-File: LICENSE
License-File: LICENSE.BSD2
License-File: LICENSE.MPL2
License-File: LICENSE.OpenMesh
License-File: LICENSE.pybind11
Requires-Dist: numpy
Requires-Dist: scipy
Requires-Dist: openmesh
Requires-Dist: networkx
Requires-Dist: matplotlib
